luscioustwitch/__init__.py
luscioustwitch/lushapi.py
luscioustwitch/lushevents.py
luscioustwitch/lushgql.py
luscioustwitch/lushrequests.py
luscioustwitch/lushtypes.py
luscioustwitch/lushwebsocket.py
luscioustwitch-0.4.9.dist-info/licenses/LICENSE
luscioustwitch-0.4.9.dist-info/METADATA
luscioustwitch-0.4.9.dist-info/WHEEL
luscioustwitch-0.4.9.dist-info/top_level.txt
luscioustwitch-0.4.9.dist-info/RECORD
