Metadata-Version: 2.4
Name: luscioustwitch
Version: 0.4.9
Summary: Twitch API Wrapper
Author-email: "luscious.dev" <admin@luscious.dev>
Project-URL: Homepage, https://github.com/lusciousdev/luscioustwitch
Project-URL: Bug Tracker, https://github.com/lusciousdev/luscioustwitch/issues
Classifier: Programming Language :: Python :: 3
Classifier: License :: OSI Approved :: GNU General Public License v3 (GPLv3)
Classifier: Operating System :: OS Independent
Requires-Python: >=3.8
License-File: LICENSE
Dynamic: license-file
